{"Tradicional": {"Carrera Profesional": {"Lambayeque": [{"Fecha_postulacion": 2022, "Sector": "Artes", "Porcentaje": 0.2, "Cantidad": 45}, {"Fecha_postulacion": 2022, "Sector": "Ciencias Puras", "Porcentaje": 0.3, "Cantidad": 80}, {"Fecha_postulacion": 2022, "Sector": "Ciencias Sociales y Humanidades", "Porcentaje": 17.7, "Cantidad": 4894}, {"Fecha_postulacion": 2022, "Sector": "Ciencias de la Salud", "Porcentaje": 33.5, "Cantidad": 9239}, {"Fecha_postulacion": 2022, "Sector": "Disciplinas Logísticas", "Porcentaje": 18.1, "Cantidad": 5003}, {"Fecha_postulacion": 2022, "Sector": "Ingenierías y Ciencias Aplicadas", "Porcentaje": 30.2, "Cantidad": 8330}, {"Fecha_postulacion": 2023, "Sector": "Artes", "Porcentaje": 0.3, "Cantidad": 88}, {"Fecha_postulacion": 2023, "Sector": "Ciencias Puras", "Porcentaje": 0.7, "Cantidad": 243}, {"Fecha_postulacion": 2023, "Sector": "Ciencias Sociales y Humanidades", "Porcentaje": 17.9, "Cantidad": 5796}, {"Fecha_postulacion": 2023, "Sector": "Ciencias de la Salud", "Porcentaje": 35.0, "Cantidad": 11369}, {"Fecha_postulacion": 2023, "Sector": "Disciplinas Logísticas", "Porcentaje": 16.1, "Cantidad": 5240}, {"Fecha_postulacion": 2023, "Sector": "Ingenierías y Ciencias Aplicadas", "Porcentaje": 30.0, "Cantidad": 9722}, {"Fecha_postulacion": 2024, "Sector": "Artes", "Porcentaje": 0.7, "Cantidad": 266}, {"Fecha_postulacion": 2024, "Sector": "Ciencias Puras", "Porcentaje": 1.4, "Cantidad": 539}, {"Fecha_postulacion": 2024, "Sector": "Ciencias Sociales y Humanidades", "Porcentaje": 19.5, "Cantidad": 7581}, {"Fecha_postulacion": 2024, "Sector": "Ciencias de la Salud", "Porcentaje": 35.6, "Cantidad": 13821}, {"Fecha_postulacion": 2024, "Sector": "Disciplinas Logísticas", "Porcentaje": 14.6, "Cantidad": 5673}, {"Fecha_postulacion": 2024, "Sector": "Ingenierías y Ciencias Aplicadas", "Porcentaje": 28.2, "Cantidad": 10938}, {"Fecha_postulacion": 2025, "Sector": "Artes", "Porcentaje": 0.8, "Cantidad": 317}, {"Fecha_postulacion": 2025, "Sector": "Ciencias Puras", "Porcentaje": 1.5, "Cantidad": 601}, {"Fecha_postulacion": 2025, "Sector": "Ciencias Sociales y Humanidades", "Porcentaje": 22.0, "Cantidad": 8618}, {"Fecha_postulacion": 2025, "Sector": "Ciencias de la Salud", "Porcentaje": 34.0, "Cantidad": 13310}, {"Fecha_postulacion": 2025, "Sector": "Disciplinas Logísticas", "Porcentaje": 14.9, "Cantidad": 5850}, {"Fecha_postulacion": 2025, "Sector": "Ingenierías y Ciencias Aplicadas", "Porcentaje": 26.7, "Cantidad": 10449}]}, "Segunda Especialidad": {"Lambayeque": [{"Fecha_postulacion": 2022, "Sector": "Artes", "Porcentaje": 0.0, "Cantidad": 0}, {"Fecha_postulacion": 2022, "Sector": "Ciencias Puras", "Porcentaje": 0.5, "Cantidad": 4}, {"Fecha_postulacion": 2022, "Sector": "Ciencias Sociales y Humanidades", "Porcentaje": 28.9, "Cantidad": 213}, {"Fecha_postulacion": 2022, "Sector": "Ciencias de la Salud", "Porcentaje": 67.6, "Cantidad": 498}, {"Fecha_postulacion": 2022, "Sector": "Disciplinas Logísticas", "Porcentaje": 2.6, "Cantidad": 19}, {"Fecha_postulacion": 2022, "Sector": "Ingenierías y Ciencias Aplicadas", "Porcentaje": 0.4, "Cantidad": 3}, {"Fecha_postulacion": 2023, "Sector": "Artes", "Porcentaje": 0.0, "Cantidad": 0}, {"Fecha_postulacion": 2023, "Sector": "Ciencias Puras", "Porcentaje": 0.6, "Cantidad": 5}, {"Fecha_postulacion": 2023, "Sector": "Ciencias Sociales y Humanidades", "Porcentaje": 44.2, "Cantidad": 357}, {"Fecha_postulacion": 2023, "Sector": "Ciencias de la Salud", "Porcentaje": 53.8, "Cantidad": 435}, {"Fecha_postulacion": 2023, "Sector": "Disciplinas Logísticas", "Porcentaje": 1.0, "Cantidad": 8}, {"Fecha_postulacion": 2023, "Sector": "Ingenierías y Ciencias Aplicadas", "Porcentaje": 0.4, "Cantidad": 3}, {"Fecha_postulacion": 2024, "Sector": "Artes", "Porcentaje": 0.0, "Cantidad": 0}, {"Fecha_postulacion": 2024, "Sector": "Ciencias Puras", "Porcentaje": 0.5, "Cantidad": 6}, {"Fecha_postulacion": 2024, "Sector": "Ciencias Sociales y Humanidades", "Porcentaje": 48.2, "Cantidad": 565}, {"Fecha_postulacion": 2024, "Sector": "Ciencias de la Salud", "Porcentaje": 48.3, "Cantidad": 567}, {"Fecha_postulacion": 2024, "Sector": "Disciplinas Logísticas", "Porcentaje": 2.5, "Cantidad": 29}, {"Fecha_postulacion": 2024, "Sector": "Ingenierías y Ciencias Aplicadas", "Porcentaje": 0.5, "Cantidad": 6}]}, "Maestría": {"Lambayeque": [{"Fecha_postulacion": 2022, "Sector": "Artes", "Porcentaje": 0.0, "Cantidad": 0}, {"Fecha_postulacion": 2022, "Sector": "Ciencias Puras", "Porcentaje": 1.8, "Cantidad": 64}, {"Fecha_postulacion": 2022, "Sector": "Ciencias Sociales y Humanidades", "Porcentaje": 27.8, "Cantidad": 1001}, {"Fecha_postulacion": 2022, "Sector": "Ciencias de la Salud", "Porcentaje": 23.4, "Cantidad": 844}, {"Fecha_postulacion": 2022, "Sector": "Disciplinas Logísticas", "Porcentaje": 36.8, "Cantidad": 1327}, {"Fecha_postulacion": 2022, "Sector": "Ingenierías y Ciencias Aplicadas", "Porcentaje": 10.2, "Cantidad": 368}, {"Fecha_postulacion": 2023, "Sector": "Artes", "Porcentaje": 0.1, "Cantidad": 2}, {"Fecha_postulacion": 2023, "Sector": "Ciencias Puras", "Porcentaje": 1.7, "Cantidad": 52}, {"Fecha_postulacion": 2023, "Sector": "Ciencias Sociales y Humanidades", "Porcentaje": 28.4, "Cantidad": 893}, {"Fecha_postulacion": 2023, "Sector": "Ciencias de la Salud", "Porcentaje": 22.6, "Cantidad": 711}, {"Fecha_postulacion": 2023, "Sector": "Disciplinas Logísticas", "Porcentaje": 38.2, "Cantidad": 1201}, {"Fecha_postulacion": 2023, "Sector": "Ingenierías y Ciencias Aplicadas", "Porcentaje": 9.1, "Cantidad": 287}, {"Fecha_postulacion": 2024, "Sector": "Artes", "Porcentaje": 0.1, "Cantidad": 4}, {"Fecha_postulacion": 2024, "Sector": "Ciencias Puras", "Porcentaje": 1.2, "Cantidad": 46}, {"Fecha_postulacion": 2024, "Sector": "Ciencias Sociales y Humanidades", "Porcentaje": 31.3, "Cantidad": 1155}, {"Fecha_postulacion": 2024, "Sector": "Ciencias de la Salud", "Porcentaje": 19.4, "Cantidad": 717}, {"Fecha_postulacion": 2024, "Sector": "Disciplinas Logísticas", "Porcentaje": 35.7, "Cantidad": 1317}, {"Fecha_postulacion": 2024, "Sector": "Ingenierías y Ciencias Aplicadas", "Porcentaje": 12.2, "Cantidad": 448}]}, "Doctorado": {"Lambayeque": [{"Fecha_postulacion": 2022, "Sector": "Artes", "Porcentaje": 0.0, "Cantidad": 0}, {"Fecha_postulacion": 2022, "Sector": "Ciencias Puras", "Porcentaje": 3.7, "Cantidad": 11}, {"Fecha_postulacion": 2022, "Sector": "Ciencias Sociales y Humanidades", "Porcentaje": 44.1, "Cantidad": 132}, {"Fecha_postulacion": 2022, "Sector": "Ciencias de la Salud", "Porcentaje": 10.7, "Cantidad": 32}, {"Fecha_postulacion": 2022, "Sector": "Disciplinas Logísticas", "Porcentaje": 35.5, "Cantidad": 106}, {"Fecha_postulacion": 2022, "Sector": "Ingenierías y Ciencias Aplicadas", "Porcentaje": 6.0, "Cantidad": 18}, {"Fecha_postulacion": 2023, "Sector": "Artes", "Porcentaje": 0.0, "Cantidad": 0}, {"Fecha_postulacion": 2023, "Sector": "Ciencias Puras", "Porcentaje": 5.6, "Cantidad": 13}, {"Fecha_postulacion": 2023, "Sector": "Ciencias Sociales y Humanidades", "Porcentaje": 41.5, "Cantidad": 97}, {"Fecha_postulacion": 2023, "Sector": "Ciencias de la Salud", "Porcentaje": 8.5, "Cantidad": 20}, {"Fecha_postulacion": 2023, "Sector": "Disciplinas Logísticas", "Porcentaje": 37.2, "Cantidad": 87}, {"Fecha_postulacion": 2023, "Sector": "Ingenierías y Ciencias Aplicadas", "Porcentaje": 7.3, "Cantidad": 17}, {"Fecha_postulacion": 2024, "Sector": "Artes", "Porcentaje": 0.0, "Cantidad": 0}, {"Fecha_postulacion": 2024, "Sector": "Ciencias Puras", "Porcentaje": 10.8, "Cantidad": 34}, {"Fecha_postulacion": 2024, "Sector": "Ciencias Sociales y Humanidades", "Porcentaje": 38.4, "Cantidad": 121}, {"Fecha_postulacion": 2024, "Sector": "Ciencias de la Salud", "Porcentaje": 11.7, "Cantidad": 37}, {"Fecha_postulacion": 2024, "Sector": "Disciplinas Logísticas", "Porcentaje": 31.4, "Cantidad": 99}, {"Fecha_postulacion": 2024, "Sector": "Ingenierías y Ciencias Aplicadas", "Porcentaje": 7.6, "Cantidad": 24}]}}, "OCDE": {"Carrera Profesional": {"Lambayeque": [{"Fecha_postulacion": 2022, "Sector": "Ciencias Agrícolas", "Porcentaje": 0.2, "Cantidad": 66}, {"Fecha_postulacion": 2022, "Sector": "Ciencias Médicas y de la Salud", "Porcentaje": 24.5, "Cantidad": 6768}, {"Fecha_postulacion": 2022, "Sector": "Ciencias Naturales", "Porcentaje": 0.3, "Cantidad": 80}, {"Fecha_postulacion": 2022, "Sector": "Ciencias Sociales", "Porcentaje": 44.7, "Cantidad": 12320}, {"Fecha_postulacion": 2022, "Sector": "Humanidades", "Porcentaje": 0.2, "Cantidad": 52}, {"Fecha_postulacion": 2022, "Sector": "Ingenierías y Tecnología", "Porcentaje": 30.1, "Cantidad": 8305}, {"Fecha_postulacion": 2023, "Sector": "Ciencias Agrícolas", "Porcentaje": 0.7, "Cantidad": 228}, {"Fecha_postulacion": 2023, "Sector": "Ciencias Médicas y de la Salud", "Porcentaje": 25.2, "Cantidad": 8177}, {"Fecha_postulacion": 2023, "Sector": "Ciencias Naturales", "Porcentaje": 0.7, "Cantidad": 243}, {"Fecha_postulacion": 2023, "Sector": "Ciencias Sociales", "Porcentaje": 43.3, "Cantidad": 14066}, {"Fecha_postulacion": 2023, "Sector": "Humanidades", "Porcentaje": 0.4, "Cantidad": 121}, {"Fecha_postulacion": 2023, "Sector": "Ingenierías y Tecnología", "Porcentaje": 29.6, "Cantidad": 9623}, {"Fecha_postulacion": 2024, "Sector": "Ciencias Agrícolas", "Porcentaje": 1.3, "Cantidad": 494}, {"Fecha_postulacion": 2024, "Sector": "Ciencias Médicas y de la Salud", "Porcentaje": 27.9, "Cantidad": 10833}, {"Fecha_postulacion": 2024, "Sector": "Ciencias Naturales", "Porcentaje": 1.4, "Cantidad": 540}, {"Fecha_postulacion": 2024, "Sector": "Ciencias Sociales", "Porcentaje": 41.2, "Cantidad": 15980}, {"Fecha_postulacion": 2024, "Sector": "Humanidades", "Porcentaje": 0.8, "Cantidad": 293}, {"Fecha_postulacion": 2024, "Sector": "Ingenierías y Tecnología", "Porcentaje": 27.5, "Cantidad": 10678}, {"Fecha_postulacion": 2025, "Sector": "Ciencias Agrícolas", "Porcentaje": 1.5, "Cantidad": 584}, {"Fecha_postulacion": 2025, "Sector": "Ciencias Médicas y de la Salud", "Porcentaje": 26.5, "Cantidad": 10372}, {"Fecha_postulacion": 2025, "Sector": "Ciencias Naturales", "Porcentaje": 1.5, "Cantidad": 601}, {"Fecha_postulacion": 2025, "Sector": "Ciencias Sociales", "Porcentaje": 43.6, "Cantidad": 17054}, {"Fecha_postulacion": 2025, "Sector": "Humanidades", "Porcentaje": 1.0, "Cantidad": 383}, {"Fecha_postulacion": 2025, "Sector": "Ingenierías y Tecnología", "Porcentaje": 25.9, "Cantidad": 10151}]}, "Segunda Especialidad": {"Lambayeque": [{"Fecha_postulacion": 2022, "Sector": "Ciencias Agrícolas", "Porcentaje": 0.0, "Cantidad": 0}, {"Fecha_postulacion": 2022, "Sector": "Ciencias Médicas y de la Salud", "Porcentaje": 66.9, "Cantidad": 493}, {"Fecha_postulacion": 2022, "Sector": "Ciencias Naturales", "Porcentaje": 0.8, "Cantidad": 6}, {"Fecha_postulacion": 2022, "Sector": "Ciencias Sociales", "Porcentaje": 31.3, "Cantidad": 231}, {"Fecha_postulacion": 2022, "Sector": "Humanidades", "Porcentaje": 0.5, "Cantidad": 4}, {"Fecha_postulacion": 2022, "Sector": "Ingenierías y Tecnología", "Porcentaje": 0.4, "Cantidad": 3}, {"Fecha_postulacion": 2023, "Sector": "Ciencias Agrícolas", "Porcentaje": 0.0, "Cantidad": 0}, {"Fecha_postulacion": 2023, "Sector": "Ciencias Médicas y de la Salud", "Porcentaje": 54.0, "Cantidad": 436}, {"Fecha_postulacion": 2023, "Sector": "Ciencias Naturales", "Porcentaje": 0.6, "Cantidad": 5}, {"Fecha_postulacion": 2023, "Sector": "Ciencias Sociales", "Porcentaje": 44.8, "Cantidad": 362}, {"Fecha_postulacion": 2023, "Sector": "Humanidades", "Porcentaje": 0.2, "Cantidad": 2}, {"Fecha_postulacion": 2023, "Sector": "Ingenierías y Tecnología", "Porcentaje": 0.4, "Cantidad": 3}, {"Fecha_postulacion": 2024, "Sector": "Ciencias Agrícolas", "Porcentaje": 0.0, "Cantidad": 0}, {"Fecha_postulacion": 2024, "Sector": "Ciencias Médicas y de la Salud", "Porcentaje": 47.2, "Cantidad": 554}, {"Fecha_postulacion": 2024, "Sector": "Ciencias Naturales", "Porcentaje": 0.7, "Cantidad": 8}, {"Fecha_postulacion": 2024, "Sector": "Ciencias Sociales", "Porcentaje": 50.4, "Cantidad": 591}, {"Fecha_postulacion": 2024, "Sector": "Humanidades", "Porcentaje": 1.4, "Cantidad": 16}, {"Fecha_postulacion": 2024, "Sector": "Ingenierías y Tecnología", "Porcentaje": 0.3, "Cantidad": 4}]}, "Maestría": {"Lambayeque": [{"Fecha_postulacion": 2022, "Sector": "Ciencias Agrícolas", "Porcentaje": 0.3, "Cantidad": 11}, {"Fecha_postulacion": 2022, "Sector": "Ciencias Médicas y de la Salud", "Porcentaje": 18.6, "Cantidad": 669}, {"Fecha_postulacion": 2022, "Sector": "Ciencias Naturales", "Porcentaje": 1.7, "Cantidad": 62}, {"Fecha_postulacion": 2022, "Sector": "Ciencias Sociales", "Porcentaje": 69.1, "Cantidad": 2491}, {"Fecha_postulacion": 2022, "Sector": "Humanidades", "Porcentaje": 0.2, "Cantidad": 9}, {"Fecha_postulacion": 2022, "Sector": "Ingenierías y Tecnología", "Porcentaje": 10.0, "Cantidad": 362}, {"Fecha_postulacion": 2023, "Sector": "Ciencias Agrícolas", "Porcentaje": 0.2, "Cantidad": 7}, {"Fecha_postulacion": 2023, "Sector": "Ciencias Médicas y de la Salud", "Porcentaje": 18.1, "Cantidad": 568}, {"Fecha_postulacion": 2023, "Sector": "Ciencias Naturales", "Porcentaje": 1.7, "Cantidad": 52}, {"Fecha_postulacion": 2023, "Sector": "Ciencias Sociales", "Porcentaje": 70.9, "Cantidad": 2231}, {"Fecha_postulacion": 2023, "Sector": "Humanidades", "Porcentaje": 0.1, "Cantidad": 4}, {"Fecha_postulacion": 2023, "Sector": "Ingenierías y Tecnología", "Porcentaje": 9.0, "Cantidad": 284}, {"Fecha_postulacion": 2024, "Sector": "Ciencias Agrícolas", "Porcentaje": 0.2, "Cantidad": 7}, {"Fecha_postulacion": 2024, "Sector": "Ciencias Médicas y de la Salud", "Porcentaje": 17.2, "Cantidad": 635}, {"Fecha_postulacion": 2024, "Sector": "Ciencias Naturales", "Porcentaje": 1.2, "Cantidad": 46}, {"Fecha_postulacion": 2024, "Sector": "Ciencias Sociales", "Porcentaje": 68.9, "Cantidad": 2540}, {"Fecha_postulacion": 2024, "Sector": "Humanidades", "Porcentaje": 0.4, "Cantidad": 15}, {"Fecha_postulacion": 2024, "Sector": "Ingenierías y Tecnología", "Porcentaje": 12.0, "Cantidad": 444}]}, "Doctorado": {"Lambayeque": [{"Fecha_postulacion": 2022, "Sector": "Ciencias Agrícolas", "Porcentaje": 0.3, "Cantidad": 1}, {"Fecha_postulacion": 2022, "Sector": "Ciencias Médicas y de la Salud", "Porcentaje": 6.4, "Cantidad": 19}, {"Fecha_postulacion": 2022, "Sector": "Ciencias Naturales", "Porcentaje": 3.7, "Cantidad": 11}, {"Fecha_postulacion": 2022, "Sector": "Ciencias Sociales", "Porcentaje": 83.3, "Cantidad": 249}, {"Fecha_postulacion": 2022, "Sector": "Humanidades", "Porcentaje": 0.7, "Cantidad": 2}, {"Fecha_postulacion": 2022, "Sector": "Ingenierías y Tecnología", "Porcentaje": 5.7, "Cantidad": 17}, {"Fecha_postulacion": 2023, "Sector": "Ciencias Agrícolas", "Porcentaje": 0.0, "Cantidad": 0}, {"Fecha_postulacion": 2023, "Sector": "Ciencias Médicas y de la Salud", "Porcentaje": 7.3, "Cantidad": 17}, {"Fecha_postulacion": 2023, "Sector": "Ciencias Naturales", "Porcentaje": 5.6, "Cantidad": 13}, {"Fecha_postulacion": 2023, "Sector": "Ciencias Sociales", "Porcentaje": 79.1, "Cantidad": 185}, {"Fecha_postulacion": 2023, "Sector": "Humanidades", "Porcentaje": 0.9, "Cantidad": 2}, {"Fecha_postulacion": 2023, "Sector": "Ingenierías y Tecnología", "Porcentaje": 7.3, "Cantidad": 17}, {"Fecha_postulacion": 2024, "Sector": "Ciencias Agrícolas", "Porcentaje": 0.3, "Cantidad": 1}, {"Fecha_postulacion": 2024, "Sector": "Ciencias Médicas y de la Salud", "Porcentaje": 6.7, "Cantidad": 21}, {"Fecha_postulacion": 2024, "Sector": "Ciencias Naturales", "Porcentaje": 10.8, "Cantidad": 34}, {"Fecha_postulacion": 2024, "Sector": "Ciencias Sociales", "Porcentaje": 74.3, "Cantidad": 234}, {"Fecha_postulacion": 2024, "Sector": "Humanidades", "Porcentaje": 0.6, "Cantidad": 2}, {"Fecha_postulacion": 2024, "Sector": "Ingenierías y Tecnología", "Porcentaje": 7.3, "Cantidad": 23}]}}}