{"Carrera Profesional": [{"año": 2022, "Público": 45.95, "Privado": 54.05, "Público_cantidad": 371390, "Privado_cantidad": 436940}, {"año": 2023, "Público": 49.43, "Privado": 50.57, "Público_cantidad": 451803, "Privado_cantidad": 462281}, {"año": 2024, "Público": 47.69, "Privado": 52.31, "Público_cantidad": 436487, "Privado_cantidad": 478791}, {"año": 2025, "Público": 44.44, "Privado": 55.56, "Público_cantidad": 430864, "Privado_cantidad": 538619}], "Segunda Especialidad": [{"año": 2022, "Público": 38.79, "Privado": 61.21, "Público_cantidad": 7113, "Privado_cantidad": 11226}, {"año": 2023, "Público": 34.73, "Privado": 65.27, "Público_cantidad": 6523, "Privado_cantidad": 12260}, {"año": 2024, "Público": 21.75, "Privado": 78.25, "Público_cantidad": 5377, "Privado_cantidad": 19346}], "Maestría": [{"año": 2022, "Público": 38.88, "Privado": 61.12, "Público_cantidad": 30211, "Privado_cantidad": 47485}, {"año": 2023, "Público": 34.08, "Privado": 65.92, "Público_cantidad": 24256, "Privado_cantidad": 46927}, {"año": 2024, "Público": 33.88, "Privado": 66.12, "Público_cantidad": 27189, "Privado_cantidad": 53071}], "Doctorado": [{"año": 2022, "Público": 56.43, "Privado": 43.57, "Público_cantidad": 3643, "Privado_cantidad": 2813}, {"año": 2023, "Público": 52.44, "Privado": 47.56, "Público_cantidad": 2804, "Privado_cantidad": 2543}, {"año": 2024, "Público": 58.5, "Privado": 41.5, "Público_cantidad": 3968, "Privado_cantidad": 2815}]}